aiorum/__init__.py
aiorum/bot.py
aiorum/dispatcher.py
aiorum/api/__init__.py
aiorum/api/api_client.py
aiorum/api/api_references.py
aiorum/api/manager.py
aiorum/models/__init__.py
aiorum/models/models.py
aiorum/utils/__init__.py
aiorum/utils/formatter.py
aiorum/utils/html_stripper.py
aiorum/utils/token.py
aiorum-1.0.3.dist-info/licenses/LICENSE
aiorum-1.0.3.dist-info/METADATA
aiorum-1.0.3.dist-info/WHEEL
aiorum-1.0.3.dist-info/top_level.txt
aiorum-1.0.3.dist-info/RECORD
